{"cameraMode":{"drawMode":0,"name":"Shaded","section":"Shading Mode"},"sceneLighting":false,"audioPlay":false,"sceneViewState":{"m_AlwaysRefresh":false,"showFog":true,"showSkybox":false,"showFlares":true,"showImageEffects":true,"showParticleSystems":true,"showVisualEffectGraphs":true,"m_FxEnabled":true},"in2DMode":false,"pivot":{"x":-1.1920928955078126e-7,"y":0.7535274624824524,"z":-0.016363799571990968},"rotation":{"x":0.4074575901031494,"y":-0.5307451486587524,"z":0.3231416940689087,"w":0.669230043888092},"size":4.975510597229004,"orthographic":false}